<?xml version="1.0" encoding="windows-1252"?>
<XMI xmi.version="1.1" xmlns:UML="omg.org/UML1.3" timestamp="2018-09-15 22:07:10">
	<XMI.header>
		<XMI.documentation>
			<XMI.exporter>Enterprise Architect</XMI.exporter>
			<XMI.exporterVersion>2.5</XMI.exporterVersion>
		</XMI.documentation>
	</XMI.header>
	<XMI.content>
		<UML:Model name="EA Model" xmi.id="MX_EAID_761315B2_51DF_4fe9_9E5C_12D7FEAC1583">
			<UML:Namespace.ownedElement>
				<UML:Class name="EARootClass" xmi.id="EAID_11111111_5487_4080_A7F4_41526CB0AA00" isRoot="true" isLeaf="false" isAbstract="false"/>
				<UML:Package name="sqlexecutorclient" xmi.id="EAPK_761315B2_51DF_4fe9_9E5C_12D7FEAC1583" isRoot="false" isLeaf="false" isAbstract="false" visibility="public">
					<UML:ModelElement.taggedValue>
						<UML:TaggedValue tag="parent" value="EAPK_EF1B4AAC_95B8_476c_99AE_970F6EE7FD8E"/>
						<UML:TaggedValue tag="created" value="2018-09-15 21:50:46"/>
						<UML:TaggedValue tag="modified" value="2018-09-15 21:50:46"/>
						<UML:TaggedValue tag="iscontrolled" value="TRUE"/>
						<UML:TaggedValue tag="xmlpath" value="C:\Java\StehlaVYS\ea\java\provysdb\sqlexecutorclient.xml"/>
						<UML:TaggedValue tag="lastsavedate" value="2018-09-15 22:07:10"/>
						<UML:TaggedValue tag="version" value="1.0"/>
						<UML:TaggedValue tag="isprotected" value="FALSE"/>
						<UML:TaggedValue tag="usedtd" value="FALSE"/>
						<UML:TaggedValue tag="owner" value="stehlik"/>
						<UML:TaggedValue tag="xmiver" value="Enterprise Architect XMI/UML 1.3"/>
						<UML:TaggedValue tag="logxml" value="FALSE"/>
						<UML:TaggedValue tag="packageFlags" value="Recurse=1;CRC=0;"/>
						<UML:TaggedValue tag="batchsave" value="1"/>
						<UML:TaggedValue tag="batchload" value="1"/>
						<UML:TaggedValue tag="phase" value="1.0"/>
						<UML:TaggedValue tag="status" value="Proposed"/>
						<UML:TaggedValue tag="author" value="stehlik"/>
						<UML:TaggedValue tag="complexity" value="1"/>
						<UML:TaggedValue tag="ea_stype" value="Public"/>
						<UML:TaggedValue tag="tpos" value="0"/>
						<UML:TaggedValue tag="gentype" value="Java"/>
					</UML:ModelElement.taggedValue>
					<UML:Namespace.ownedElement>
						<UML:Class name="ExecutorFactoryClient" xmi.id="EAID_0A67EEB1_C2AC_492b_A863_08C51FFBB928" visibility="public" namespace="EAPK_761315B2_51DF_4fe9_9E5C_12D7FEAC1583" isRoot="false" isLeaf="false" isAbstract="false" isActive="false">
							<UML:ModelElement.taggedValue>
								<UML:TaggedValue tag="documentation" value="Factory for creation of SQL executors, working as client against remote ProvysDb service. &#xA;"/>
								<UML:TaggedValue tag="isSpecification" value="false"/>
								<UML:TaggedValue tag="ea_stype" value="Class"/>
								<UML:TaggedValue tag="ea_ntype" value="0"/>
								<UML:TaggedValue tag="version" value="1.0"/>
								<UML:TaggedValue tag="package" value="EAPK_761315B2_51DF_4fe9_9E5C_12D7FEAC1583"/>
								<UML:TaggedValue tag="date_created" value="2018-09-15 21:50:46"/>
								<UML:TaggedValue tag="date_modified" value="2018-09-15 21:50:46"/>
								<UML:TaggedValue tag="genfile" value="C:\Java\StehlaVYS\java\provysdb\provysdb-client\src\main\java\com\provys\provysdb\sqlexecutorclient\ExecutorFactoryClient.java"/>
								<UML:TaggedValue tag="gentype" value="Java"/>
								<UML:TaggedValue tag="tagged" value="0"/>
								<UML:TaggedValue tag="package_name" value="sqlexecutorclient"/>
								<UML:TaggedValue tag="phase" value="1.0"/>
								<UML:TaggedValue tag="author" value="stehlik"/>
								<UML:TaggedValue tag="complexity" value="1"/>
								<UML:TaggedValue tag="status" value="Proposed"/>
								<UML:TaggedValue tag="tpos" value="0"/>
								<UML:TaggedValue tag="ea_localid" value="121"/>
								<UML:TaggedValue tag="ea_eleType" value="element"/>
								<UML:TaggedValue tag="eventflags" value="OBJ=1555;"/>
								<UML:TaggedValue tag="style" value="BackColor=-1;BorderColor=-1;BorderWidth=-1;FontColor=-1;VSwimLanes=1;HSwimLanes=1;BorderStyle=0;"/>
							</UML:ModelElement.taggedValue>
							<UML:Classifier.feature>
								<UML:Attribute name="client" changeable="frozen" visibility="private" ownerScope="instance" targetScope="instance">
									<UML:Attribute.initialValue>
										<UML:Expression body="ClientBuilder.newClient()"/>
									</UML:Attribute.initialValue>
									<UML:StructuralFeature.type>
										<UML:Classifier xmi.idref="eaxmiid0"/>
									</UML:StructuralFeature.type>
									<UML:ModelElement.taggedValue>
										<UML:TaggedValue tag="type" value="Client"/>
										<UML:TaggedValue tag="derived" value="0"/>
										<UML:TaggedValue tag="containment" value="Not Specified"/>
										<UML:TaggedValue tag="length" value="0"/>
										<UML:TaggedValue tag="ordered" value="0"/>
										<UML:TaggedValue tag="static" value="0"/>
										<UML:TaggedValue tag="collection" value="false"/>
										<UML:TaggedValue tag="position" value="0"/>
										<UML:TaggedValue tag="lowerBound" value="1"/>
										<UML:TaggedValue tag="upperBound" value="1"/>
										<UML:TaggedValue tag="duplicates" value="0"/>
										<UML:TaggedValue tag="ea_guid" value="{82B61B18-08C3-4690-B09D-981B2E44DDA0}"/>
										<UML:TaggedValue tag="ea_localid" value="83"/>
										<UML:TaggedValue tag="styleex" value="volatile=0;union=0;"/>
									</UML:ModelElement.taggedValue>
								</UML:Attribute>
								<UML:Operation name="getJsonQueryExecutor" visibility="public" ownerScope="instance" isQuery="false" concurrency="sequential">
									<UML:ModelElement.taggedValue>
										<UML:TaggedValue tag="type" value="JsonQueryExecutor"/>
										<UML:TaggedValue tag="const" value="false"/>
										<UML:TaggedValue tag="synchronised" value="0"/>
										<UML:TaggedValue tag="concurrency" value="Sequential"/>
										<UML:TaggedValue tag="position" value="0"/>
										<UML:TaggedValue tag="returnarray" value="0"/>
										<UML:TaggedValue tag="pure" value="0"/>
										<UML:TaggedValue tag="ea_guid" value="{1E0FD819-F005-490f-98AB-E82824BD3D23}"/>
										<UML:TaggedValue tag="ea_localid" value="309"/>
										<UML:TaggedValue tag="annotations" value="@Override" xmi.id="EAID_055A0B80_DCA0_425b_91C0_B39476F97AB2"/>
									</UML:ModelElement.taggedValue>
									<UML:BehavioralFeature.parameter>
										<UML:Parameter kind="return" visibility="public">
											<UML:Parameter.type>
												<UML:Classifier xmi.idref="EAID_9D22D8CE_2635_420e_9ABD_D02BE7FB6109"/>
											</UML:Parameter.type>
											<UML:ModelElement.taggedValue>
												<UML:TaggedValue tag="pos" value="0"/>
												<UML:TaggedValue tag="type" value="JsonQueryExecutor"/>
												<UML:TaggedValue tag="const" value="0"/>
												<UML:TaggedValue tag="classifier" value="EAID_9D22D8CE_2635_420e_9ABD_D02BE7FB6109"/>
												<UML:TaggedValue tag="ea_guid" value="{RETURNID-F005-490f-98AB-E82824BD3D23}"/>
											</UML:ModelElement.taggedValue>
											<UML:Parameter.defaultValue>
												<UML:Expression/>
											</UML:Parameter.defaultValue>
										</UML:Parameter>
									</UML:BehavioralFeature.parameter>
								</UML:Operation>
								<UML:Operation name="getJsonQueryExecutor" visibility="public" ownerScope="instance" isQuery="false" concurrency="sequential">
									<UML:ModelElement.taggedValue>
										<UML:TaggedValue tag="type" value="JsonQueryExecutor"/>
										<UML:TaggedValue tag="const" value="false"/>
										<UML:TaggedValue tag="synchronised" value="0"/>
										<UML:TaggedValue tag="concurrency" value="Sequential"/>
										<UML:TaggedValue tag="position" value="1"/>
										<UML:TaggedValue tag="returnarray" value="0"/>
										<UML:TaggedValue tag="pure" value="0"/>
										<UML:TaggedValue tag="ea_guid" value="{08963C2C-DBA4-4f01-82D5-EE107F8B3444}"/>
										<UML:TaggedValue tag="ea_localid" value="308"/>
										<UML:TaggedValue tag="annotations" value="@Override" xmi.id="EAID_7144A0D1_6B02_4e01_B1ED_9A3B49BAF09F"/>
									</UML:ModelElement.taggedValue>
									<UML:BehavioralFeature.parameter>
										<UML:Parameter kind="return" visibility="public">
											<UML:Parameter.type>
												<UML:Classifier xmi.idref="EAID_9D22D8CE_2635_420e_9ABD_D02BE7FB6109"/>
											</UML:Parameter.type>
											<UML:ModelElement.taggedValue>
												<UML:TaggedValue tag="pos" value="0"/>
												<UML:TaggedValue tag="type" value="JsonQueryExecutor"/>
												<UML:TaggedValue tag="const" value="0"/>
												<UML:TaggedValue tag="classifier" value="EAID_9D22D8CE_2635_420e_9ABD_D02BE7FB6109"/>
												<UML:TaggedValue tag="ea_guid" value="{RETURNID-DBA4-4f01-82D5-EE107F8B3444}"/>
											</UML:ModelElement.taggedValue>
											<UML:Parameter.defaultValue>
												<UML:Expression/>
											</UML:Parameter.defaultValue>
										</UML:Parameter>
										<UML:Parameter name="sqlCall" kind="in" visibility="public">
											<UML:Parameter.type>
												<UML:Classifier xmi.idref="EAID_28F23804_0BFC_4caa_BE91_7F8C39510F3E"/>
											</UML:Parameter.type>
											<UML:ModelElement.taggedValue>
												<UML:TaggedValue tag="pos" value="0"/>
												<UML:TaggedValue tag="type" value="SQLCall"/>
												<UML:TaggedValue tag="const" value="0"/>
												<UML:TaggedValue tag="classifier" value="EAID_28F23804_0BFC_4caa_BE91_7F8C39510F3E"/>
												<UML:TaggedValue tag="ea_guid" value="{45B42A16-F7BE-4709-B852-A89AB427695D}"/>
											</UML:ModelElement.taggedValue>
											<UML:Parameter.defaultValue>
												<UML:Expression/>
											</UML:Parameter.defaultValue>
										</UML:Parameter>
									</UML:BehavioralFeature.parameter>
								</UML:Operation>
								<UML:Operation name="getMapQueryExecutor" visibility="public" ownerScope="instance" isQuery="false" concurrency="sequential">
									<UML:ModelElement.taggedValue>
										<UML:TaggedValue tag="type" value="MapQueryExecutor"/>
										<UML:TaggedValue tag="const" value="false"/>
										<UML:TaggedValue tag="synchronised" value="0"/>
										<UML:TaggedValue tag="concurrency" value="Sequential"/>
										<UML:TaggedValue tag="position" value="2"/>
										<UML:TaggedValue tag="returnarray" value="0"/>
										<UML:TaggedValue tag="pure" value="0"/>
										<UML:TaggedValue tag="ea_guid" value="{C408268C-1F5D-44be-B463-B71A43406E73}"/>
										<UML:TaggedValue tag="ea_localid" value="311"/>
										<UML:TaggedValue tag="annotations" value="@Override" xmi.id="EAID_72C8AE9D_F321_47ec_912C_80B4B567D4CA"/>
									</UML:ModelElement.taggedValue>
									<UML:BehavioralFeature.parameter>
										<UML:Parameter kind="return" visibility="public">
											<UML:Parameter.type>
												<UML:Classifier xmi.idref="EAID_262B336D_5716_4cfc_BA03_3FFD7D6854C4"/>
											</UML:Parameter.type>
											<UML:ModelElement.taggedValue>
												<UML:TaggedValue tag="pos" value="0"/>
												<UML:TaggedValue tag="type" value="MapQueryExecutor"/>
												<UML:TaggedValue tag="const" value="0"/>
												<UML:TaggedValue tag="classifier" value="EAID_262B336D_5716_4cfc_BA03_3FFD7D6854C4"/>
												<UML:TaggedValue tag="ea_guid" value="{RETURNID-1F5D-44be-B463-B71A43406E73}"/>
											</UML:ModelElement.taggedValue>
											<UML:Parameter.defaultValue>
												<UML:Expression/>
											</UML:Parameter.defaultValue>
										</UML:Parameter>
									</UML:BehavioralFeature.parameter>
								</UML:Operation>
								<UML:Operation name="getMapQueryExecutor" visibility="public" ownerScope="instance" isQuery="false" concurrency="sequential">
									<UML:ModelElement.taggedValue>
										<UML:TaggedValue tag="type" value="MapQueryExecutor"/>
										<UML:TaggedValue tag="const" value="false"/>
										<UML:TaggedValue tag="synchronised" value="0"/>
										<UML:TaggedValue tag="concurrency" value="Sequential"/>
										<UML:TaggedValue tag="position" value="3"/>
										<UML:TaggedValue tag="returnarray" value="0"/>
										<UML:TaggedValue tag="pure" value="0"/>
										<UML:TaggedValue tag="ea_guid" value="{8AA7960D-3A5C-4c6c-A709-C9AB2BF1A801}"/>
										<UML:TaggedValue tag="ea_localid" value="310"/>
										<UML:TaggedValue tag="annotations" value="@Override" xmi.id="EAID_A98FF894_450B_4611_9C7D_852EC52B10A5"/>
									</UML:ModelElement.taggedValue>
									<UML:BehavioralFeature.parameter>
										<UML:Parameter kind="return" visibility="public">
											<UML:Parameter.type>
												<UML:Classifier xmi.idref="EAID_262B336D_5716_4cfc_BA03_3FFD7D6854C4"/>
											</UML:Parameter.type>
											<UML:ModelElement.taggedValue>
												<UML:TaggedValue tag="pos" value="0"/>
												<UML:TaggedValue tag="type" value="MapQueryExecutor"/>
												<UML:TaggedValue tag="const" value="0"/>
												<UML:TaggedValue tag="classifier" value="EAID_262B336D_5716_4cfc_BA03_3FFD7D6854C4"/>
												<UML:TaggedValue tag="ea_guid" value="{RETURNID-3A5C-4c6c-A709-C9AB2BF1A801}"/>
											</UML:ModelElement.taggedValue>
											<UML:Parameter.defaultValue>
												<UML:Expression/>
											</UML:Parameter.defaultValue>
										</UML:Parameter>
										<UML:Parameter name="sqlCall" kind="in" visibility="public">
											<UML:Parameter.type>
												<UML:Classifier xmi.idref="EAID_28F23804_0BFC_4caa_BE91_7F8C39510F3E"/>
											</UML:Parameter.type>
											<UML:ModelElement.taggedValue>
												<UML:TaggedValue tag="pos" value="0"/>
												<UML:TaggedValue tag="type" value="SQLCall"/>
												<UML:TaggedValue tag="const" value="0"/>
												<UML:TaggedValue tag="classifier" value="EAID_28F23804_0BFC_4caa_BE91_7F8C39510F3E"/>
												<UML:TaggedValue tag="ea_guid" value="{9AD8DCFE-952C-42cd-9B2D-958397D27280}"/>
											</UML:ModelElement.taggedValue>
											<UML:Parameter.defaultValue>
												<UML:Expression/>
											</UML:Parameter.defaultValue>
										</UML:Parameter>
									</UML:BehavioralFeature.parameter>
								</UML:Operation>
							</UML:Classifier.feature>
						</UML:Class>
						<UML:Dependency client="EAID_0A67EEB1_C2AC_492b_A863_08C51FFBB928" supplier="EAID_EC56ADEA_E8B8_440a_B394_B11D6DBCB4E1" xmi.id="EAID_BD8342DB_D356_41cd_B462_3FA9BB5E7974" visibility="public">
							<UML:ModelElement.taggedValue>
								<UML:TaggedValue tag="style" value="3"/>
								<UML:TaggedValue tag="ea_type" value="Realisation"/>
								<UML:TaggedValue tag="direction" value="Source -&gt; Destination"/>
								<UML:TaggedValue tag="linemode" value="3"/>
								<UML:TaggedValue tag="linecolor" value="-1"/>
								<UML:TaggedValue tag="linewidth" value="0"/>
								<UML:TaggedValue tag="seqno" value="0"/>
								<UML:TaggedValue tag="headStyle" value="0"/>
								<UML:TaggedValue tag="lineStyle" value="0"/>
								<UML:TaggedValue tag="ea_localid" value="76"/>
								<UML:TaggedValue tag="ea_sourceName" value="ExecutorFactoryClient"/>
								<UML:TaggedValue tag="ea_targetName" value="ExecutorFactory"/>
								<UML:TaggedValue tag="ea_sourceType" value="Class"/>
								<UML:TaggedValue tag="ea_targetType" value="Interface"/>
								<UML:TaggedValue tag="ea_sourceID" value="121"/>
								<UML:TaggedValue tag="ea_targetID" value="113"/>
								<UML:TaggedValue tag="src_visibility" value="Public"/>
								<UML:TaggedValue tag="src_aggregation" value="0"/>
								<UML:TaggedValue tag="src_isOrdered" value="false"/>
								<UML:TaggedValue tag="src_targetScope" value="instance"/>
								<UML:TaggedValue tag="src_changeable" value="none"/>
								<UML:TaggedValue tag="src_isNavigable" value="false"/>
								<UML:TaggedValue tag="src_containment" value="Unspecified"/>
								<UML:TaggedValue tag="src_style" value="Union=0;Derived=0;AllowDuplicates=0;Owned=0;Navigable=Non-Navigable;"/>
								<UML:TaggedValue tag="dst_visibility" value="Public"/>
								<UML:TaggedValue tag="dst_aggregation" value="0"/>
								<UML:TaggedValue tag="dst_isOrdered" value="false"/>
								<UML:TaggedValue tag="dst_targetScope" value="instance"/>
								<UML:TaggedValue tag="dst_changeable" value="none"/>
								<UML:TaggedValue tag="dst_isNavigable" value="true"/>
								<UML:TaggedValue tag="dst_containment" value="Unspecified"/>
								<UML:TaggedValue tag="dst_style" value="Union=0;Derived=0;AllowDuplicates=0;Owned=0;Navigable=Navigable;"/>
								<UML:TaggedValue tag="virtualInheritance" value="0"/>
							</UML:ModelElement.taggedValue>
						</UML:Dependency>
						<UML:Class name="MapQueryExecutorClient" xmi.id="EAID_7A5CEA3D_C075_4c8b_BC1E_77F652A698EA" visibility="public" namespace="EAPK_761315B2_51DF_4fe9_9E5C_12D7FEAC1583" isRoot="false" isLeaf="false" isAbstract="false" isActive="false">
							<UML:ModelElement.taggedValue>
								<UML:TaggedValue tag="documentation" value="Implementation class for JsonQueryExecutor against remote database service &#xA;"/>
								<UML:TaggedValue tag="isSpecification" value="false"/>
								<UML:TaggedValue tag="ea_stype" value="Class"/>
								<UML:TaggedValue tag="ea_ntype" value="0"/>
								<UML:TaggedValue tag="version" value="1.0"/>
								<UML:TaggedValue tag="package" value="EAPK_761315B2_51DF_4fe9_9E5C_12D7FEAC1583"/>
								<UML:TaggedValue tag="date_created" value="2018-09-15 21:50:46"/>
								<UML:TaggedValue tag="date_modified" value="2018-09-15 21:50:46"/>
								<UML:TaggedValue tag="genfile" value="C:\Java\StehlaVYS\java\provysdb\provysdb-client\src\main\java\com\provys\provysdb\sqlexecutorclient\MapQueryExecutorClient.java"/>
								<UML:TaggedValue tag="gentype" value="Java"/>
								<UML:TaggedValue tag="tagged" value="0"/>
								<UML:TaggedValue tag="package_name" value="sqlexecutorclient"/>
								<UML:TaggedValue tag="phase" value="1.0"/>
								<UML:TaggedValue tag="author" value="stehlik"/>
								<UML:TaggedValue tag="complexity" value="1"/>
								<UML:TaggedValue tag="status" value="Proposed"/>
								<UML:TaggedValue tag="tpos" value="0"/>
								<UML:TaggedValue tag="ea_localid" value="123"/>
								<UML:TaggedValue tag="ea_eleType" value="element"/>
								<UML:TaggedValue tag="eventflags" value="OBJ=1555;"/>
								<UML:TaggedValue tag="style" value="BackColor=-1;BorderColor=-1;BorderWidth=-1;FontColor=-1;VSwimLanes=1;HSwimLanes=1;BorderStyle=0;"/>
							</UML:ModelElement.taggedValue>
							<UML:Classifier.feature>
								<UML:Attribute name="client" changeable="frozen" visibility="private" ownerScope="instance" targetScope="instance">
									<UML:Attribute.initialValue>
										<UML:Expression/>
									</UML:Attribute.initialValue>
									<UML:StructuralFeature.type>
										<UML:Classifier xmi.idref="eaxmiid0"/>
									</UML:StructuralFeature.type>
									<UML:ModelElement.taggedValue>
										<UML:TaggedValue tag="type" value="Client"/>
										<UML:TaggedValue tag="derived" value="0"/>
										<UML:TaggedValue tag="containment" value="Not Specified"/>
										<UML:TaggedValue tag="length" value="0"/>
										<UML:TaggedValue tag="ordered" value="0"/>
										<UML:TaggedValue tag="static" value="0"/>
										<UML:TaggedValue tag="collection" value="false"/>
										<UML:TaggedValue tag="position" value="0"/>
										<UML:TaggedValue tag="lowerBound" value="1"/>
										<UML:TaggedValue tag="upperBound" value="1"/>
										<UML:TaggedValue tag="duplicates" value="0"/>
										<UML:TaggedValue tag="ea_guid" value="{5FD62EF8-AA8C-404f-873D-621924EF204D}"/>
										<UML:TaggedValue tag="ea_localid" value="87"/>
										<UML:TaggedValue tag="styleex" value="volatile=0;union=0;"/>
									</UML:ModelElement.taggedValue>
								</UML:Attribute>
								<UML:Attribute name="data" changeable="none" visibility="private" ownerScope="instance" targetScope="instance">
									<UML:Attribute.initialValue>
										<UML:Expression/>
									</UML:Attribute.initialValue>
									<UML:StructuralFeature.type>
										<UML:Classifier xmi.idref="eaxmiid1"/>
									</UML:StructuralFeature.type>
									<UML:ModelElement.taggedValue>
										<UML:TaggedValue tag="type" value="List&lt;Map&lt;String, Object&gt;&gt;"/>
										<UML:TaggedValue tag="derived" value="0"/>
										<UML:TaggedValue tag="containment" value="Not Specified"/>
										<UML:TaggedValue tag="length" value="0"/>
										<UML:TaggedValue tag="ordered" value="0"/>
										<UML:TaggedValue tag="static" value="0"/>
										<UML:TaggedValue tag="collection" value="false"/>
										<UML:TaggedValue tag="position" value="2"/>
										<UML:TaggedValue tag="lowerBound" value="1"/>
										<UML:TaggedValue tag="upperBound" value="1"/>
										<UML:TaggedValue tag="duplicates" value="0"/>
										<UML:TaggedValue tag="ea_guid" value="{A7F68643-3677-4c43-86A8-539E5495D07A}"/>
										<UML:TaggedValue tag="ea_localid" value="88"/>
										<UML:TaggedValue tag="styleex" value="volatile=0;union=0;"/>
									</UML:ModelElement.taggedValue>
								</UML:Attribute>
								<UML:Attribute name="sqlCall" changeable="none" visibility="private" ownerScope="instance" targetScope="instance">
									<UML:Attribute.initialValue>
										<UML:Expression/>
									</UML:Attribute.initialValue>
									<UML:StructuralFeature.type>
										<UML:Classifier xmi.idref="EAID_28F23804_0BFC_4caa_BE91_7F8C39510F3E"/>
									</UML:StructuralFeature.type>
									<UML:ModelElement.taggedValue>
										<UML:TaggedValue tag="type" value="SQLCall"/>
										<UML:TaggedValue tag="derived" value="0"/>
										<UML:TaggedValue tag="containment" value="Not Specified"/>
										<UML:TaggedValue tag="length" value="0"/>
										<UML:TaggedValue tag="ordered" value="0"/>
										<UML:TaggedValue tag="static" value="0"/>
										<UML:TaggedValue tag="collection" value="false"/>
										<UML:TaggedValue tag="position" value="1"/>
										<UML:TaggedValue tag="lowerBound" value="1"/>
										<UML:TaggedValue tag="upperBound" value="1"/>
										<UML:TaggedValue tag="duplicates" value="0"/>
										<UML:TaggedValue tag="ea_guid" value="{31BAAAA5-27CC-496e-9238-8EF705FD047A}"/>
										<UML:TaggedValue tag="ea_localid" value="89"/>
										<UML:TaggedValue tag="styleex" value="volatile=0;union=0;"/>
									</UML:ModelElement.taggedValue>
								</UML:Attribute>
								<UML:Operation name="executeQuery" visibility="public" ownerScope="instance" isQuery="false" concurrency="sequential">
									<UML:ModelElement.taggedValue>
										<UML:TaggedValue tag="type" value="List&lt;Map&lt;String, Object&gt;&gt;"/>
										<UML:TaggedValue tag="const" value="false"/>
										<UML:TaggedValue tag="synchronised" value="0"/>
										<UML:TaggedValue tag="concurrency" value="Sequential"/>
										<UML:TaggedValue tag="position" value="2"/>
										<UML:TaggedValue tag="returnarray" value="0"/>
										<UML:TaggedValue tag="pure" value="0"/>
										<UML:TaggedValue tag="ea_guid" value="{B7746B07-7BD0-4e6e-97FF-25886282B18A}"/>
										<UML:TaggedValue tag="ea_localid" value="318"/>
										<UML:TaggedValue tag="annotations" value="@Override" xmi.id="EAID_006EFC4F_EC7A_42f8_B40E_9F27BF7ED39C"/>
									</UML:ModelElement.taggedValue>
									<UML:BehavioralFeature.parameter>
										<UML:Parameter kind="return" visibility="public">
											<UML:Parameter.type>
												<UML:Classifier xmi.idref="eaxmiid1"/>
											</UML:Parameter.type>
											<UML:ModelElement.taggedValue>
												<UML:TaggedValue tag="pos" value="0"/>
												<UML:TaggedValue tag="type" value="List&lt;Map&lt;String, Object&gt;&gt;"/>
												<UML:TaggedValue tag="const" value="0"/>
												<UML:TaggedValue tag="ea_guid" value="{RETURNID-7BD0-4e6e-97FF-25886282B18A}"/>
											</UML:ModelElement.taggedValue>
											<UML:Parameter.defaultValue>
												<UML:Expression/>
											</UML:Parameter.defaultValue>
										</UML:Parameter>
									</UML:BehavioralFeature.parameter>
								</UML:Operation>
								<UML:Operation name="getData" visibility="public" ownerScope="instance" isQuery="false" concurrency="sequential">
									<UML:ModelElement.taggedValue>
										<UML:TaggedValue tag="type" value="List&lt;Map&lt;String, Object&gt;&gt;"/>
										<UML:TaggedValue tag="const" value="false"/>
										<UML:TaggedValue tag="synchronised" value="0"/>
										<UML:TaggedValue tag="concurrency" value="Sequential"/>
										<UML:TaggedValue tag="position" value="3"/>
										<UML:TaggedValue tag="returnarray" value="0"/>
										<UML:TaggedValue tag="pure" value="0"/>
										<UML:TaggedValue tag="ea_guid" value="{AC732A7B-8922-420f-BCAB-589B670AF4AF}"/>
										<UML:TaggedValue tag="ea_localid" value="319"/>
										<UML:TaggedValue tag="annotations" value="@Override" xmi.id="EAID_CE577718_29FF_4f7d_8A90_45DFB82EC9D4"/>
									</UML:ModelElement.taggedValue>
									<UML:BehavioralFeature.parameter>
										<UML:Parameter kind="return" visibility="public">
											<UML:Parameter.type>
												<UML:Classifier xmi.idref="eaxmiid1"/>
											</UML:Parameter.type>
											<UML:ModelElement.taggedValue>
												<UML:TaggedValue tag="pos" value="0"/>
												<UML:TaggedValue tag="type" value="List&lt;Map&lt;String, Object&gt;&gt;"/>
												<UML:TaggedValue tag="const" value="0"/>
												<UML:TaggedValue tag="ea_guid" value="{RETURNID-8922-420f-BCAB-589B670AF4AF}"/>
											</UML:ModelElement.taggedValue>
											<UML:Parameter.defaultValue>
												<UML:Expression/>
											</UML:Parameter.defaultValue>
										</UML:Parameter>
									</UML:BehavioralFeature.parameter>
								</UML:Operation>
								<UML:Operation name="getSqlCall" visibility="public" ownerScope="instance" isQuery="false" concurrency="sequential">
									<UML:ModelElement.taggedValue>
										<UML:TaggedValue tag="type" value="SQLCall"/>
										<UML:TaggedValue tag="const" value="false"/>
										<UML:TaggedValue tag="synchronised" value="0"/>
										<UML:TaggedValue tag="concurrency" value="Sequential"/>
										<UML:TaggedValue tag="position" value="4"/>
										<UML:TaggedValue tag="returnarray" value="0"/>
										<UML:TaggedValue tag="pure" value="0"/>
										<UML:TaggedValue tag="ea_guid" value="{9EF5DDA8-316E-4585-AC40-073880F0A9E1}"/>
										<UML:TaggedValue tag="ea_localid" value="320"/>
										<UML:TaggedValue tag="annotations" value="@Override" xmi.id="EAID_A23B4B47_E2AD_4e72_A478_F7490A2B211E"/>
									</UML:ModelElement.taggedValue>
									<UML:BehavioralFeature.parameter>
										<UML:Parameter kind="return" visibility="public">
											<UML:Parameter.type>
												<UML:Classifier xmi.idref="EAID_28F23804_0BFC_4caa_BE91_7F8C39510F3E"/>
											</UML:Parameter.type>
											<UML:ModelElement.taggedValue>
												<UML:TaggedValue tag="pos" value="0"/>
												<UML:TaggedValue tag="type" value="SQLCall"/>
												<UML:TaggedValue tag="const" value="0"/>
												<UML:TaggedValue tag="classifier" value="EAID_28F23804_0BFC_4caa_BE91_7F8C39510F3E"/>
												<UML:TaggedValue tag="ea_guid" value="{RETURNID-316E-4585-AC40-073880F0A9E1}"/>
											</UML:ModelElement.taggedValue>
											<UML:Parameter.defaultValue>
												<UML:Expression/>
											</UML:Parameter.defaultValue>
										</UML:Parameter>
									</UML:BehavioralFeature.parameter>
								</UML:Operation>
								<UML:Operation name="MapQueryExecutorClient" visibility="protected" ownerScope="instance" isQuery="false" concurrency="sequential">
									<UML:ModelElement.taggedValue>
										<UML:TaggedValue tag="const" value="false"/>
										<UML:TaggedValue tag="synchronised" value="0"/>
										<UML:TaggedValue tag="concurrency" value="Sequential"/>
										<UML:TaggedValue tag="position" value="0"/>
										<UML:TaggedValue tag="returnarray" value="0"/>
										<UML:TaggedValue tag="pure" value="0"/>
										<UML:TaggedValue tag="ea_guid" value="{D9F11670-50C6-40ad-853F-219C011DFD2D}"/>
										<UML:TaggedValue tag="ea_localid" value="322"/>
										<UML:TaggedValue tag="scope" value="package"/>
									</UML:ModelElement.taggedValue>
									<UML:BehavioralFeature.parameter>
										<UML:Parameter kind="return" visibility="public">
											<UML:Parameter.type>
												<UML:Classifier xmi.idref="eaxmiid2"/>
											</UML:Parameter.type>
											<UML:ModelElement.taggedValue>
												<UML:TaggedValue tag="pos" value="0"/>
												<UML:TaggedValue tag="const" value="0"/>
												<UML:TaggedValue tag="ea_guid" value="{RETURNID-50C6-40ad-853F-219C011DFD2D}"/>
											</UML:ModelElement.taggedValue>
											<UML:Parameter.defaultValue>
												<UML:Expression/>
											</UML:Parameter.defaultValue>
										</UML:Parameter>
										<UML:Parameter name="client" kind="in" visibility="public">
											<UML:Parameter.type>
												<UML:Classifier xmi.idref="eaxmiid0"/>
											</UML:Parameter.type>
											<UML:ModelElement.taggedValue>
												<UML:TaggedValue tag="pos" value="0"/>
												<UML:TaggedValue tag="type" value="Client"/>
												<UML:TaggedValue tag="const" value="0"/>
												<UML:TaggedValue tag="ea_guid" value="{71B1582E-4BA0-4a57-8E8A-2CEA80A413B2}"/>
											</UML:ModelElement.taggedValue>
											<UML:Parameter.defaultValue>
												<UML:Expression/>
											</UML:Parameter.defaultValue>
										</UML:Parameter>
									</UML:BehavioralFeature.parameter>
								</UML:Operation>
								<UML:Operation name="MapQueryExecutorClient" visibility="protected" ownerScope="instance" isQuery="false" concurrency="sequential">
									<UML:ModelElement.taggedValue>
										<UML:TaggedValue tag="const" value="false"/>
										<UML:TaggedValue tag="synchronised" value="0"/>
										<UML:TaggedValue tag="concurrency" value="Sequential"/>
										<UML:TaggedValue tag="position" value="1"/>
										<UML:TaggedValue tag="returnarray" value="0"/>
										<UML:TaggedValue tag="pure" value="0"/>
										<UML:TaggedValue tag="ea_guid" value="{54177E45-1E7D-43f3-9688-BE5BA733FEEB}"/>
										<UML:TaggedValue tag="ea_localid" value="321"/>
										<UML:TaggedValue tag="scope" value="package"/>
									</UML:ModelElement.taggedValue>
									<UML:BehavioralFeature.parameter>
										<UML:Parameter kind="return" visibility="public">
											<UML:Parameter.type>
												<UML:Classifier xmi.idref="eaxmiid2"/>
											</UML:Parameter.type>
											<UML:ModelElement.taggedValue>
												<UML:TaggedValue tag="pos" value="0"/>
												<UML:TaggedValue tag="const" value="0"/>
												<UML:TaggedValue tag="ea_guid" value="{RETURNID-1E7D-43f3-9688-BE5BA733FEEB}"/>
											</UML:ModelElement.taggedValue>
											<UML:Parameter.defaultValue>
												<UML:Expression/>
											</UML:Parameter.defaultValue>
										</UML:Parameter>
										<UML:Parameter name="client" kind="in" visibility="public">
											<UML:Parameter.type>
												<UML:Classifier xmi.idref="eaxmiid0"/>
											</UML:Parameter.type>
											<UML:ModelElement.taggedValue>
												<UML:TaggedValue tag="pos" value="0"/>
												<UML:TaggedValue tag="type" value="Client"/>
												<UML:TaggedValue tag="const" value="0"/>
												<UML:TaggedValue tag="ea_guid" value="{1A69A3EA-0F22-4c60-8A7F-C2F0244AC413}"/>
											</UML:ModelElement.taggedValue>
											<UML:Parameter.defaultValue>
												<UML:Expression/>
											</UML:Parameter.defaultValue>
										</UML:Parameter>
										<UML:Parameter name="sqlCall" kind="in" visibility="public">
											<UML:Parameter.type>
												<UML:Classifier xmi.idref="EAID_28F23804_0BFC_4caa_BE91_7F8C39510F3E"/>
											</UML:Parameter.type>
											<UML:ModelElement.taggedValue>
												<UML:TaggedValue tag="pos" value="1"/>
												<UML:TaggedValue tag="type" value="SQLCall"/>
												<UML:TaggedValue tag="const" value="0"/>
												<UML:TaggedValue tag="classifier" value="EAID_28F23804_0BFC_4caa_BE91_7F8C39510F3E"/>
												<UML:TaggedValue tag="ea_guid" value="{5EEA39FB-6CB3-41f3-AFCD-8040BCEC623C}"/>
											</UML:ModelElement.taggedValue>
											<UML:Parameter.defaultValue>
												<UML:Expression/>
											</UML:Parameter.defaultValue>
										</UML:Parameter>
									</UML:BehavioralFeature.parameter>
								</UML:Operation>
								<UML:Operation name="setSqlCall" visibility="public" ownerScope="instance" isQuery="false" concurrency="sequential">
									<UML:ModelElement.taggedValue>
										<UML:TaggedValue tag="type" value="void"/>
										<UML:TaggedValue tag="const" value="false"/>
										<UML:TaggedValue tag="synchronised" value="0"/>
										<UML:TaggedValue tag="concurrency" value="Sequential"/>
										<UML:TaggedValue tag="position" value="5"/>
										<UML:TaggedValue tag="returnarray" value="0"/>
										<UML:TaggedValue tag="pure" value="0"/>
										<UML:TaggedValue tag="ea_guid" value="{0F9CB699-9FF9-4f0c-9BAB-D8196DF7165B}"/>
										<UML:TaggedValue tag="ea_localid" value="323"/>
										<UML:TaggedValue tag="annotations" value="@Override" xmi.id="EAID_93F076BD_DD46_4c59_AC0D_CAA48801E0C9"/>
									</UML:ModelElement.taggedValue>
									<UML:BehavioralFeature.parameter>
										<UML:Parameter kind="return" visibility="public">
											<UML:Parameter.type>
												<UML:Classifier xmi.idref="eaxmiid3"/>
											</UML:Parameter.type>
											<UML:ModelElement.taggedValue>
												<UML:TaggedValue tag="pos" value="0"/>
												<UML:TaggedValue tag="type" value="void"/>
												<UML:TaggedValue tag="const" value="0"/>
												<UML:TaggedValue tag="ea_guid" value="{RETURNID-9FF9-4f0c-9BAB-D8196DF7165B}"/>
											</UML:ModelElement.taggedValue>
											<UML:Parameter.defaultValue>
												<UML:Expression/>
											</UML:Parameter.defaultValue>
										</UML:Parameter>
										<UML:Parameter name="sqlCall" kind="in" visibility="public">
											<UML:Parameter.type>
												<UML:Classifier xmi.idref="EAID_28F23804_0BFC_4caa_BE91_7F8C39510F3E"/>
											</UML:Parameter.type>
											<UML:ModelElement.taggedValue>
												<UML:TaggedValue tag="pos" value="0"/>
												<UML:TaggedValue tag="type" value="SQLCall"/>
												<UML:TaggedValue tag="const" value="0"/>
												<UML:TaggedValue tag="classifier" value="EAID_28F23804_0BFC_4caa_BE91_7F8C39510F3E"/>
												<UML:TaggedValue tag="ea_guid" value="{EA505909-862E-4335-8777-7271CBE773A1}"/>
											</UML:ModelElement.taggedValue>
											<UML:Parameter.defaultValue>
												<UML:Expression/>
											</UML:Parameter.defaultValue>
										</UML:Parameter>
									</UML:BehavioralFeature.parameter>
								</UML:Operation>
							</UML:Classifier.feature>
						</UML:Class>
						<UML:Association xmi.id="EAID_0089E4DA_294D_4898_9AE0_36031BEE3682" visibility="public" isRoot="false" isLeaf="false" isAbstract="false">
							<UML:ModelElement.taggedValue>
								<UML:TaggedValue tag="style" value="3"/>
								<UML:TaggedValue tag="ea_type" value="Association"/>
								<UML:TaggedValue tag="direction" value="Source -&gt; Destination"/>
								<UML:TaggedValue tag="linemode" value="3"/>
								<UML:TaggedValue tag="linecolor" value="-1"/>
								<UML:TaggedValue tag="linewidth" value="0"/>
								<UML:TaggedValue tag="seqno" value="0"/>
								<UML:TaggedValue tag="headStyle" value="0"/>
								<UML:TaggedValue tag="lineStyle" value="0"/>
								<UML:TaggedValue tag="ea_localid" value="79"/>
								<UML:TaggedValue tag="ea_sourceName" value="MapQueryExecutorClient"/>
								<UML:TaggedValue tag="ea_targetName" value="SQLCall"/>
								<UML:TaggedValue tag="ea_sourceType" value="Class"/>
								<UML:TaggedValue tag="ea_targetType" value="Class"/>
								<UML:TaggedValue tag="ea_sourceID" value="123"/>
								<UML:TaggedValue tag="ea_targetID" value="111"/>
								<UML:TaggedValue tag="virtualInheritance" value="0"/>
								<UML:TaggedValue tag="rt" value="-sqlCall"/>
							</UML:ModelElement.taggedValue>
							<UML:Association.connection>
								<UML:AssociationEnd visibility="public" aggregation="none" isOrdered="false" targetScope="instance" changeable="none" isNavigable="false" type="EAID_7A5CEA3D_C075_4c8b_BC1E_77F652A698EA">
									<UML:ModelElement.taggedValue>
										<UML:TaggedValue tag="containment" value="Unspecified"/>
										<UML:TaggedValue tag="sourcestyle" value="Union=0;Derived=0;AllowDuplicates=0;Owned=0;Navigable=Non-Navigable;"/>
										<UML:TaggedValue tag="ea_end" value="source"/>
									</UML:ModelElement.taggedValue>
								</UML:AssociationEnd>
								<UML:AssociationEnd visibility="private" name="sqlCall" aggregation="none" isOrdered="false" targetScope="instance" changeable="none" isNavigable="true" type="EAID_28F23804_0BFC_4caa_BE91_7F8C39510F3E">
									<UML:ModelElement.taggedValue>
										<UML:TaggedValue tag="containment" value="Unspecified"/>
										<UML:TaggedValue tag="type" value="Private"/>
										<UML:TaggedValue tag="deststyle" value="Union=0;Derived=0;AllowDuplicates=0;Owned=0;Navigable=Navigable;"/>
										<UML:TaggedValue tag="ea_end" value="target"/>
									</UML:ModelElement.taggedValue>
								</UML:AssociationEnd>
							</UML:Association.connection>
						</UML:Association>
						<UML:Dependency client="EAID_7A5CEA3D_C075_4c8b_BC1E_77F652A698EA" supplier="EAID_262B336D_5716_4cfc_BA03_3FFD7D6854C4" xmi.id="EAID_80954EF1_3B7D_4215_8178_E85508C4F01F" visibility="public">
							<UML:ModelElement.taggedValue>
								<UML:TaggedValue tag="style" value="3"/>
								<UML:TaggedValue tag="ea_type" value="Realisation"/>
								<UML:TaggedValue tag="direction" value="Source -&gt; Destination"/>
								<UML:TaggedValue tag="linemode" value="3"/>
								<UML:TaggedValue tag="linecolor" value="-1"/>
								<UML:TaggedValue tag="linewidth" value="0"/>
								<UML:TaggedValue tag="seqno" value="0"/>
								<UML:TaggedValue tag="headStyle" value="0"/>
								<UML:TaggedValue tag="lineStyle" value="0"/>
								<UML:TaggedValue tag="ea_localid" value="80"/>
								<UML:TaggedValue tag="ea_sourceName" value="MapQueryExecutorClient"/>
								<UML:TaggedValue tag="ea_targetName" value="MapQueryExecutor"/>
								<UML:TaggedValue tag="ea_sourceType" value="Class"/>
								<UML:TaggedValue tag="ea_targetType" value="Interface"/>
								<UML:TaggedValue tag="ea_sourceID" value="123"/>
								<UML:TaggedValue tag="ea_targetID" value="115"/>
								<UML:TaggedValue tag="src_visibility" value="Public"/>
								<UML:TaggedValue tag="src_aggregation" value="0"/>
								<UML:TaggedValue tag="src_isOrdered" value="false"/>
								<UML:TaggedValue tag="src_targetScope" value="instance"/>
								<UML:TaggedValue tag="src_changeable" value="none"/>
								<UML:TaggedValue tag="src_isNavigable" value="false"/>
								<UML:TaggedValue tag="src_containment" value="Unspecified"/>
								<UML:TaggedValue tag="src_style" value="Union=0;Derived=0;AllowDuplicates=0;Owned=0;Navigable=Non-Navigable;"/>
								<UML:TaggedValue tag="dst_visibility" value="Public"/>
								<UML:TaggedValue tag="dst_aggregation" value="0"/>
								<UML:TaggedValue tag="dst_isOrdered" value="false"/>
								<UML:TaggedValue tag="dst_targetScope" value="instance"/>
								<UML:TaggedValue tag="dst_changeable" value="none"/>
								<UML:TaggedValue tag="dst_isNavigable" value="true"/>
								<UML:TaggedValue tag="dst_containment" value="Unspecified"/>
								<UML:TaggedValue tag="dst_style" value="Union=0;Derived=0;AllowDuplicates=0;Owned=0;Navigable=Navigable;"/>
								<UML:TaggedValue tag="virtualInheritance" value="0"/>
							</UML:ModelElement.taggedValue>
						</UML:Dependency>
						<UML:Class name="JsonQueryExecutorClient" xmi.id="EAID_FFB327C0_8E60_45de_AA10_4AA8DFEA2C8E" visibility="public" namespace="EAPK_761315B2_51DF_4fe9_9E5C_12D7FEAC1583" isRoot="false" isLeaf="false" isAbstract="false" isActive="false">
							<UML:ModelElement.taggedValue>
								<UML:TaggedValue tag="documentation" value="Implementation class for JsonQueryExecutor against remote database service &#xA;"/>
								<UML:TaggedValue tag="isSpecification" value="false"/>
								<UML:TaggedValue tag="ea_stype" value="Class"/>
								<UML:TaggedValue tag="ea_ntype" value="0"/>
								<UML:TaggedValue tag="version" value="1.0"/>
								<UML:TaggedValue tag="package" value="EAPK_761315B2_51DF_4fe9_9E5C_12D7FEAC1583"/>
								<UML:TaggedValue tag="date_created" value="2018-09-15 21:50:46"/>
								<UML:TaggedValue tag="date_modified" value="2018-09-15 21:50:46"/>
								<UML:TaggedValue tag="genfile" value="C:\Java\StehlaVYS\java\provysdb\provysdb-client\src\main\java\com\provys\provysdb\sqlexecutorclient\JsonQueryExecutorClient.java"/>
								<UML:TaggedValue tag="gentype" value="Java"/>
								<UML:TaggedValue tag="tagged" value="0"/>
								<UML:TaggedValue tag="package_name" value="sqlexecutorclient"/>
								<UML:TaggedValue tag="phase" value="1.0"/>
								<UML:TaggedValue tag="author" value="stehlik"/>
								<UML:TaggedValue tag="complexity" value="1"/>
								<UML:TaggedValue tag="status" value="Proposed"/>
								<UML:TaggedValue tag="tpos" value="0"/>
								<UML:TaggedValue tag="ea_localid" value="122"/>
								<UML:TaggedValue tag="ea_eleType" value="element"/>
								<UML:TaggedValue tag="eventflags" value="OBJ=1555;"/>
								<UML:TaggedValue tag="style" value="BackColor=-1;BorderColor=-1;BorderWidth=-1;FontColor=-1;VSwimLanes=1;HSwimLanes=1;BorderStyle=0;"/>
							</UML:ModelElement.taggedValue>
							<UML:Classifier.feature>
								<UML:Attribute name="client" changeable="frozen" visibility="private" ownerScope="instance" targetScope="instance">
									<UML:Attribute.initialValue>
										<UML:Expression/>
									</UML:Attribute.initialValue>
									<UML:StructuralFeature.type>
										<UML:Classifier xmi.idref="eaxmiid0"/>
									</UML:StructuralFeature.type>
									<UML:ModelElement.taggedValue>
										<UML:TaggedValue tag="type" value="Client"/>
										<UML:TaggedValue tag="derived" value="0"/>
										<UML:TaggedValue tag="containment" value="Not Specified"/>
										<UML:TaggedValue tag="length" value="0"/>
										<UML:TaggedValue tag="ordered" value="0"/>
										<UML:TaggedValue tag="static" value="0"/>
										<UML:TaggedValue tag="collection" value="false"/>
										<UML:TaggedValue tag="position" value="0"/>
										<UML:TaggedValue tag="lowerBound" value="1"/>
										<UML:TaggedValue tag="upperBound" value="1"/>
										<UML:TaggedValue tag="duplicates" value="0"/>
										<UML:TaggedValue tag="ea_guid" value="{17DC2217-AE18-4731-91A7-16E7E92539DA}"/>
										<UML:TaggedValue tag="ea_localid" value="84"/>
										<UML:TaggedValue tag="styleex" value="volatile=0;union=0;"/>
									</UML:ModelElement.taggedValue>
								</UML:Attribute>
								<UML:Attribute name="data" changeable="none" visibility="private" ownerScope="instance" targetScope="instance">
									<UML:Attribute.initialValue>
										<UML:Expression/>
									</UML:Attribute.initialValue>
									<UML:StructuralFeature.type>
										<UML:Classifier xmi.idref="eaxmiid4"/>
									</UML:StructuralFeature.type>
									<UML:ModelElement.taggedValue>
										<UML:TaggedValue tag="type" value="List&lt;JsonObject&gt;"/>
										<UML:TaggedValue tag="derived" value="0"/>
										<UML:TaggedValue tag="containment" value="Not Specified"/>
										<UML:TaggedValue tag="length" value="0"/>
										<UML:TaggedValue tag="ordered" value="0"/>
										<UML:TaggedValue tag="static" value="0"/>
										<UML:TaggedValue tag="collection" value="false"/>
										<UML:TaggedValue tag="position" value="2"/>
										<UML:TaggedValue tag="lowerBound" value="1"/>
										<UML:TaggedValue tag="upperBound" value="1"/>
										<UML:TaggedValue tag="duplicates" value="0"/>
										<UML:TaggedValue tag="ea_guid" value="{B8252419-22B2-47a2-BD28-8C734BBA393A}"/>
										<UML:TaggedValue tag="ea_localid" value="85"/>
										<UML:TaggedValue tag="styleex" value="volatile=0;union=0;"/>
									</UML:ModelElement.taggedValue>
								</UML:Attribute>
								<UML:Attribute name="sqlCall" changeable="none" visibility="private" ownerScope="instance" targetScope="instance">
									<UML:Attribute.initialValue>
										<UML:Expression/>
									</UML:Attribute.initialValue>
									<UML:StructuralFeature.type>
										<UML:Classifier xmi.idref="EAID_28F23804_0BFC_4caa_BE91_7F8C39510F3E"/>
									</UML:StructuralFeature.type>
									<UML:ModelElement.taggedValue>
										<UML:TaggedValue tag="type" value="SQLCall"/>
										<UML:TaggedValue tag="derived" value="0"/>
										<UML:TaggedValue tag="containment" value="Not Specified"/>
										<UML:TaggedValue tag="length" value="0"/>
										<UML:TaggedValue tag="ordered" value="0"/>
										<UML:TaggedValue tag="static" value="0"/>
										<UML:TaggedValue tag="collection" value="false"/>
										<UML:TaggedValue tag="position" value="1"/>
										<UML:TaggedValue tag="lowerBound" value="1"/>
										<UML:TaggedValue tag="upperBound" value="1"/>
										<UML:TaggedValue tag="duplicates" value="0"/>
										<UML:TaggedValue tag="ea_guid" value="{A1F4DC29-EAE4-4101-B8AB-1722D8EC5873}"/>
										<UML:TaggedValue tag="ea_localid" value="86"/>
										<UML:TaggedValue tag="styleex" value="volatile=0;union=0;"/>
									</UML:ModelElement.taggedValue>
								</UML:Attribute>
								<UML:Operation name="executeQuery" visibility="public" ownerScope="instance" isQuery="false" concurrency="sequential">
									<UML:ModelElement.taggedValue>
										<UML:TaggedValue tag="type" value="List&lt;JsonObject&gt;"/>
										<UML:TaggedValue tag="const" value="false"/>
										<UML:TaggedValue tag="synchronised" value="0"/>
										<UML:TaggedValue tag="concurrency" value="Sequential"/>
										<UML:TaggedValue tag="position" value="2"/>
										<UML:TaggedValue tag="returnarray" value="0"/>
										<UML:TaggedValue tag="pure" value="0"/>
										<UML:TaggedValue tag="ea_guid" value="{A447C196-6245-4b56-AC52-00C933F77E65}"/>
										<UML:TaggedValue tag="ea_localid" value="312"/>
										<UML:TaggedValue tag="annotations" value="@Override" xmi.id="EAID_26640A9C_E9E9_4fc6_A966_09FD15AD2DA4"/>
									</UML:ModelElement.taggedValue>
									<UML:BehavioralFeature.parameter>
										<UML:Parameter kind="return" visibility="public">
											<UML:Parameter.type>
												<UML:Classifier xmi.idref="eaxmiid4"/>
											</UML:Parameter.type>
											<UML:ModelElement.taggedValue>
												<UML:TaggedValue tag="pos" value="0"/>
												<UML:TaggedValue tag="type" value="List&lt;JsonObject&gt;"/>
												<UML:TaggedValue tag="const" value="0"/>
												<UML:TaggedValue tag="ea_guid" value="{RETURNID-6245-4b56-AC52-00C933F77E65}"/>
											</UML:ModelElement.taggedValue>
											<UML:Parameter.defaultValue>
												<UML:Expression/>
											</UML:Parameter.defaultValue>
										</UML:Parameter>
									</UML:BehavioralFeature.parameter>
								</UML:Operation>
								<UML:Operation name="getData" visibility="public" ownerScope="instance" isQuery="false" concurrency="sequential">
									<UML:ModelElement.taggedValue>
										<UML:TaggedValue tag="type" value="List&lt;JsonObject&gt;"/>
										<UML:TaggedValue tag="const" value="false"/>
										<UML:TaggedValue tag="synchronised" value="0"/>
										<UML:TaggedValue tag="concurrency" value="Sequential"/>
										<UML:TaggedValue tag="position" value="3"/>
										<UML:TaggedValue tag="returnarray" value="0"/>
										<UML:TaggedValue tag="pure" value="0"/>
										<UML:TaggedValue tag="ea_guid" value="{39023E5D-21D5-49eb-8D88-BE81E9766086}"/>
										<UML:TaggedValue tag="ea_localid" value="313"/>
										<UML:TaggedValue tag="annotations" value="@Override" xmi.id="EAID_242983EA_B75D_428c_A3A2_26B0A7BA0C18"/>
									</UML:ModelElement.taggedValue>
									<UML:BehavioralFeature.parameter>
										<UML:Parameter kind="return" visibility="public">
											<UML:Parameter.type>
												<UML:Classifier xmi.idref="eaxmiid4"/>
											</UML:Parameter.type>
											<UML:ModelElement.taggedValue>
												<UML:TaggedValue tag="pos" value="0"/>
												<UML:TaggedValue tag="type" value="List&lt;JsonObject&gt;"/>
												<UML:TaggedValue tag="const" value="0"/>
												<UML:TaggedValue tag="ea_guid" value="{RETURNID-21D5-49eb-8D88-BE81E9766086}"/>
											</UML:ModelElement.taggedValue>
											<UML:Parameter.defaultValue>
												<UML:Expression/>
											</UML:Parameter.defaultValue>
										</UML:Parameter>
									</UML:BehavioralFeature.parameter>
								</UML:Operation>
								<UML:Operation name="getSqlCall" visibility="public" ownerScope="instance" isQuery="false" concurrency="sequential">
									<UML:ModelElement.taggedValue>
										<UML:TaggedValue tag="type" value="SQLCall"/>
										<UML:TaggedValue tag="const" value="false"/>
										<UML:TaggedValue tag="synchronised" value="0"/>
										<UML:TaggedValue tag="concurrency" value="Sequential"/>
										<UML:TaggedValue tag="position" value="4"/>
										<UML:TaggedValue tag="returnarray" value="0"/>
										<UML:TaggedValue tag="pure" value="0"/>
										<UML:TaggedValue tag="ea_guid" value="{3EFB37F3-DFCF-4cd4-A05A-D0E34F18A428}"/>
										<UML:TaggedValue tag="ea_localid" value="314"/>
										<UML:TaggedValue tag="annotations" value="@Override" xmi.id="EAID_69ECC878_C029_4197_9002_198ECD3127BB"/>
									</UML:ModelElement.taggedValue>
									<UML:BehavioralFeature.parameter>
										<UML:Parameter kind="return" visibility="public">
											<UML:Parameter.type>
												<UML:Classifier xmi.idref="EAID_28F23804_0BFC_4caa_BE91_7F8C39510F3E"/>
											</UML:Parameter.type>
											<UML:ModelElement.taggedValue>
												<UML:TaggedValue tag="pos" value="0"/>
												<UML:TaggedValue tag="type" value="SQLCall"/>
												<UML:TaggedValue tag="const" value="0"/>
												<UML:TaggedValue tag="classifier" value="EAID_28F23804_0BFC_4caa_BE91_7F8C39510F3E"/>
												<UML:TaggedValue tag="ea_guid" value="{RETURNID-DFCF-4cd4-A05A-D0E34F18A428}"/>
											</UML:ModelElement.taggedValue>
											<UML:Parameter.defaultValue>
												<UML:Expression/>
											</UML:Parameter.defaultValue>
										</UML:Parameter>
									</UML:BehavioralFeature.parameter>
								</UML:Operation>
								<UML:Operation name="JsonQueryExecutorClient" visibility="protected" ownerScope="instance" isQuery="false" concurrency="sequential">
									<UML:ModelElement.taggedValue>
										<UML:TaggedValue tag="const" value="false"/>
										<UML:TaggedValue tag="synchronised" value="0"/>
										<UML:TaggedValue tag="concurrency" value="Sequential"/>
										<UML:TaggedValue tag="position" value="0"/>
										<UML:TaggedValue tag="returnarray" value="0"/>
										<UML:TaggedValue tag="pure" value="0"/>
										<UML:TaggedValue tag="ea_guid" value="{72EA4E09-85BE-4713-B7DB-741F6B951047}"/>
										<UML:TaggedValue tag="ea_localid" value="316"/>
										<UML:TaggedValue tag="scope" value="package"/>
									</UML:ModelElement.taggedValue>
									<UML:BehavioralFeature.parameter>
										<UML:Parameter kind="return" visibility="public">
											<UML:Parameter.type>
												<UML:Classifier xmi.idref="eaxmiid2"/>
											</UML:Parameter.type>
											<UML:ModelElement.taggedValue>
												<UML:TaggedValue tag="pos" value="0"/>
												<UML:TaggedValue tag="const" value="0"/>
												<UML:TaggedValue tag="ea_guid" value="{RETURNID-85BE-4713-B7DB-741F6B951047}"/>
											</UML:ModelElement.taggedValue>
											<UML:Parameter.defaultValue>
												<UML:Expression/>
											</UML:Parameter.defaultValue>
										</UML:Parameter>
										<UML:Parameter name="client" kind="in" visibility="public">
											<UML:Parameter.type>
												<UML:Classifier xmi.idref="eaxmiid0"/>
											</UML:Parameter.type>
											<UML:ModelElement.taggedValue>
												<UML:TaggedValue tag="pos" value="0"/>
												<UML:TaggedValue tag="type" value="Client"/>
												<UML:TaggedValue tag="const" value="0"/>
												<UML:TaggedValue tag="ea_guid" value="{F90E0C40-7C84-438f-BC76-A22CF67D2B4B}"/>
											</UML:ModelElement.taggedValue>
											<UML:Parameter.defaultValue>
												<UML:Expression/>
											</UML:Parameter.defaultValue>
										</UML:Parameter>
									</UML:BehavioralFeature.parameter>
								</UML:Operation>
								<UML:Operation name="JsonQueryExecutorClient" visibility="protected" ownerScope="instance" isQuery="false" concurrency="sequential">
									<UML:ModelElement.taggedValue>
										<UML:TaggedValue tag="const" value="false"/>
										<UML:TaggedValue tag="synchronised" value="0"/>
										<UML:TaggedValue tag="concurrency" value="Sequential"/>
										<UML:TaggedValue tag="position" value="1"/>
										<UML:TaggedValue tag="returnarray" value="0"/>
										<UML:TaggedValue tag="pure" value="0"/>
										<UML:TaggedValue tag="ea_guid" value="{55701FF9-496E-4ace-AC1D-1108100ECFC8}"/>
										<UML:TaggedValue tag="ea_localid" value="315"/>
										<UML:TaggedValue tag="scope" value="package"/>
									</UML:ModelElement.taggedValue>
									<UML:BehavioralFeature.parameter>
										<UML:Parameter kind="return" visibility="public">
											<UML:Parameter.type>
												<UML:Classifier xmi.idref="eaxmiid2"/>
											</UML:Parameter.type>
											<UML:ModelElement.taggedValue>
												<UML:TaggedValue tag="pos" value="0"/>
												<UML:TaggedValue tag="const" value="0"/>
												<UML:TaggedValue tag="ea_guid" value="{RETURNID-496E-4ace-AC1D-1108100ECFC8}"/>
											</UML:ModelElement.taggedValue>
											<UML:Parameter.defaultValue>
												<UML:Expression/>
											</UML:Parameter.defaultValue>
										</UML:Parameter>
										<UML:Parameter name="client" kind="in" visibility="public">
											<UML:Parameter.type>
												<UML:Classifier xmi.idref="eaxmiid0"/>
											</UML:Parameter.type>
											<UML:ModelElement.taggedValue>
												<UML:TaggedValue tag="pos" value="0"/>
												<UML:TaggedValue tag="type" value="Client"/>
												<UML:TaggedValue tag="const" value="0"/>
												<UML:TaggedValue tag="ea_guid" value="{A7CB08E1-103B-407f-A7FE-173B07B51517}"/>
											</UML:ModelElement.taggedValue>
											<UML:Parameter.defaultValue>
												<UML:Expression/>
											</UML:Parameter.defaultValue>
										</UML:Parameter>
										<UML:Parameter name="sqlCall" kind="in" visibility="public">
											<UML:Parameter.type>
												<UML:Classifier xmi.idref="EAID_28F23804_0BFC_4caa_BE91_7F8C39510F3E"/>
											</UML:Parameter.type>
											<UML:ModelElement.taggedValue>
												<UML:TaggedValue tag="pos" value="1"/>
												<UML:TaggedValue tag="type" value="SQLCall"/>
												<UML:TaggedValue tag="const" value="0"/>
												<UML:TaggedValue tag="classifier" value="EAID_28F23804_0BFC_4caa_BE91_7F8C39510F3E"/>
												<UML:TaggedValue tag="ea_guid" value="{00398D11-6876-4c8d-84EC-43FD6817B71B}"/>
											</UML:ModelElement.taggedValue>
											<UML:Parameter.defaultValue>
												<UML:Expression/>
											</UML:Parameter.defaultValue>
										</UML:Parameter>
									</UML:BehavioralFeature.parameter>
								</UML:Operation>
								<UML:Operation name="setSqlCall" visibility="public" ownerScope="instance" isQuery="false" concurrency="sequential">
									<UML:ModelElement.taggedValue>
										<UML:TaggedValue tag="type" value="void"/>
										<UML:TaggedValue tag="const" value="false"/>
										<UML:TaggedValue tag="synchronised" value="0"/>
										<UML:TaggedValue tag="concurrency" value="Sequential"/>
										<UML:TaggedValue tag="position" value="5"/>
										<UML:TaggedValue tag="returnarray" value="0"/>
										<UML:TaggedValue tag="pure" value="0"/>
										<UML:TaggedValue tag="ea_guid" value="{F98D0740-2B9B-465f-894B-CE04F98598AE}"/>
										<UML:TaggedValue tag="ea_localid" value="317"/>
										<UML:TaggedValue tag="annotations" value="@Override" xmi.id="EAID_AD77ED81_E3A5_4850_8A47_7F661535FD96"/>
									</UML:ModelElement.taggedValue>
									<UML:BehavioralFeature.parameter>
										<UML:Parameter kind="return" visibility="public">
											<UML:Parameter.type>
												<UML:Classifier xmi.idref="eaxmiid3"/>
											</UML:Parameter.type>
											<UML:ModelElement.taggedValue>
												<UML:TaggedValue tag="pos" value="0"/>
												<UML:TaggedValue tag="type" value="void"/>
												<UML:TaggedValue tag="const" value="0"/>
												<UML:TaggedValue tag="ea_guid" value="{RETURNID-2B9B-465f-894B-CE04F98598AE}"/>
											</UML:ModelElement.taggedValue>
											<UML:Parameter.defaultValue>
												<UML:Expression/>
											</UML:Parameter.defaultValue>
										</UML:Parameter>
										<UML:Parameter name="sqlCall" kind="in" visibility="public">
											<UML:Parameter.type>
												<UML:Classifier xmi.idref="EAID_28F23804_0BFC_4caa_BE91_7F8C39510F3E"/>
											</UML:Parameter.type>
											<UML:ModelElement.taggedValue>
												<UML:TaggedValue tag="pos" value="0"/>
												<UML:TaggedValue tag="type" value="SQLCall"/>
												<UML:TaggedValue tag="const" value="0"/>
												<UML:TaggedValue tag="classifier" value="EAID_28F23804_0BFC_4caa_BE91_7F8C39510F3E"/>
												<UML:TaggedValue tag="ea_guid" value="{2B06FBAD-3D08-40b2-BACD-339B80125BF5}"/>
											</UML:ModelElement.taggedValue>
											<UML:Parameter.defaultValue>
												<UML:Expression/>
											</UML:Parameter.defaultValue>
										</UML:Parameter>
									</UML:BehavioralFeature.parameter>
								</UML:Operation>
							</UML:Classifier.feature>
						</UML:Class>
						<UML:Association xmi.id="EAID_745C6CA6_0BCE_436b_93CC_DFD7ABD946CB" visibility="public" isRoot="false" isLeaf="false" isAbstract="false">
							<UML:ModelElement.taggedValue>
								<UML:TaggedValue tag="style" value="3"/>
								<UML:TaggedValue tag="ea_type" value="Association"/>
								<UML:TaggedValue tag="direction" value="Source -&gt; Destination"/>
								<UML:TaggedValue tag="linemode" value="3"/>
								<UML:TaggedValue tag="linecolor" value="-1"/>
								<UML:TaggedValue tag="linewidth" value="0"/>
								<UML:TaggedValue tag="seqno" value="0"/>
								<UML:TaggedValue tag="headStyle" value="0"/>
								<UML:TaggedValue tag="lineStyle" value="0"/>
								<UML:TaggedValue tag="ea_localid" value="77"/>
								<UML:TaggedValue tag="ea_sourceName" value="JsonQueryExecutorClient"/>
								<UML:TaggedValue tag="ea_targetName" value="SQLCall"/>
								<UML:TaggedValue tag="ea_sourceType" value="Class"/>
								<UML:TaggedValue tag="ea_targetType" value="Class"/>
								<UML:TaggedValue tag="ea_sourceID" value="122"/>
								<UML:TaggedValue tag="ea_targetID" value="111"/>
								<UML:TaggedValue tag="virtualInheritance" value="0"/>
								<UML:TaggedValue tag="rt" value="-sqlCall"/>
							</UML:ModelElement.taggedValue>
							<UML:Association.connection>
								<UML:AssociationEnd visibility="public" aggregation="none" isOrdered="false" targetScope="instance" changeable="none" isNavigable="false" type="EAID_FFB327C0_8E60_45de_AA10_4AA8DFEA2C8E">
									<UML:ModelElement.taggedValue>
										<UML:TaggedValue tag="containment" value="Unspecified"/>
										<UML:TaggedValue tag="sourcestyle" value="Union=0;Derived=0;AllowDuplicates=0;Owned=0;Navigable=Non-Navigable;"/>
										<UML:TaggedValue tag="ea_end" value="source"/>
									</UML:ModelElement.taggedValue>
								</UML:AssociationEnd>
								<UML:AssociationEnd visibility="private" name="sqlCall" aggregation="none" isOrdered="false" targetScope="instance" changeable="none" isNavigable="true" type="EAID_28F23804_0BFC_4caa_BE91_7F8C39510F3E">
									<UML:ModelElement.taggedValue>
										<UML:TaggedValue tag="containment" value="Unspecified"/>
										<UML:TaggedValue tag="type" value="Private"/>
										<UML:TaggedValue tag="deststyle" value="Union=0;Derived=0;AllowDuplicates=0;Owned=0;Navigable=Navigable;"/>
										<UML:TaggedValue tag="ea_end" value="target"/>
									</UML:ModelElement.taggedValue>
								</UML:AssociationEnd>
							</UML:Association.connection>
						</UML:Association>
						<UML:Dependency client="EAID_FFB327C0_8E60_45de_AA10_4AA8DFEA2C8E" supplier="EAID_9D22D8CE_2635_420e_9ABD_D02BE7FB6109" xmi.id="EAID_82B34C5A_034C_4e05_AFD8_63DC1CB051DA" visibility="public">
							<UML:ModelElement.taggedValue>
								<UML:TaggedValue tag="style" value="3"/>
								<UML:TaggedValue tag="ea_type" value="Realisation"/>
								<UML:TaggedValue tag="direction" value="Source -&gt; Destination"/>
								<UML:TaggedValue tag="linemode" value="3"/>
								<UML:TaggedValue tag="linecolor" value="-1"/>
								<UML:TaggedValue tag="linewidth" value="0"/>
								<UML:TaggedValue tag="seqno" value="0"/>
								<UML:TaggedValue tag="headStyle" value="0"/>
								<UML:TaggedValue tag="lineStyle" value="0"/>
								<UML:TaggedValue tag="ea_localid" value="78"/>
								<UML:TaggedValue tag="ea_sourceName" value="JsonQueryExecutorClient"/>
								<UML:TaggedValue tag="ea_targetName" value="JsonQueryExecutor"/>
								<UML:TaggedValue tag="ea_sourceType" value="Class"/>
								<UML:TaggedValue tag="ea_targetType" value="Interface"/>
								<UML:TaggedValue tag="ea_sourceID" value="122"/>
								<UML:TaggedValue tag="ea_targetID" value="114"/>
								<UML:TaggedValue tag="src_visibility" value="Public"/>
								<UML:TaggedValue tag="src_aggregation" value="0"/>
								<UML:TaggedValue tag="src_isOrdered" value="false"/>
								<UML:TaggedValue tag="src_targetScope" value="instance"/>
								<UML:TaggedValue tag="src_changeable" value="none"/>
								<UML:TaggedValue tag="src_isNavigable" value="false"/>
								<UML:TaggedValue tag="src_containment" value="Unspecified"/>
								<UML:TaggedValue tag="src_style" value="Union=0;Derived=0;AllowDuplicates=0;Owned=0;Navigable=Non-Navigable;"/>
								<UML:TaggedValue tag="dst_visibility" value="Public"/>
								<UML:TaggedValue tag="dst_aggregation" value="0"/>
								<UML:TaggedValue tag="dst_isOrdered" value="false"/>
								<UML:TaggedValue tag="dst_targetScope" value="instance"/>
								<UML:TaggedValue tag="dst_changeable" value="none"/>
								<UML:TaggedValue tag="dst_isNavigable" value="true"/>
								<UML:TaggedValue tag="dst_containment" value="Unspecified"/>
								<UML:TaggedValue tag="dst_style" value="Union=0;Derived=0;AllowDuplicates=0;Owned=0;Navigable=Navigable;"/>
								<UML:TaggedValue tag="virtualInheritance" value="0"/>
							</UML:ModelElement.taggedValue>
						</UML:Dependency>
					</UML:Namespace.ownedElement>
				</UML:Package>
				<UML:DataType xmi.id="eaxmiid2" visibility="private" isRoot="false" isLeaf="false" isAbstract="false"/>
				<UML:DataType xmi.id="eaxmiid0" name="Client" visibility="private" isRoot="false" isLeaf="false" isAbstract="false"/>
				<UML:DataType xmi.id="eaxmiid4" name="List&lt;JsonObject&gt;" visibility="private" isRoot="false" isLeaf="false" isAbstract="false"/>
				<UML:DataType xmi.id="eaxmiid3" name="void" visibility="private" isRoot="false" isLeaf="false" isAbstract="false"/>
				<UML:DataType xmi.id="eaxmiid1" name="List&lt;Map&lt;String, Object&gt;&gt;" visibility="private" isRoot="false" isLeaf="false" isAbstract="false"/>
			</UML:Namespace.ownedElement>
		</UML:Model>
		<UML:TaggedValue tag="annotations" xmi.id="EAID_456C6BE6_E1DB_443a_B9CC_EEF2AE058BFC" value="@ApplicationScoped" modelElement="EAID_0A67EEB1_C2AC_492b_A863_08C51FFBB928"/>
	</XMI.content>
	<XMI.difference/>
	<XMI.extensions xmi.extender="Enterprise Architect 2.5">
		<EAStub xmi.id="EAID_EC56ADEA_E8B8_440a_B394_B11D6DBCB4E1" name="ExecutorFactory" UMLType="Interface"/>
		<EAModel.paramSub/>
		<EAStub xmi.id="EAID_28F23804_0BFC_4caa_BE91_7F8C39510F3E" name="SQLCall" UMLType="Class"/>
		<EAStub xmi.id="EAID_262B336D_5716_4cfc_BA03_3FFD7D6854C4" name="MapQueryExecutor" UMLType="Interface"/>
		<EAStub xmi.id="EAID_9D22D8CE_2635_420e_9ABD_D02BE7FB6109" name="JsonQueryExecutor" UMLType="Interface"/>
	</XMI.extensions>
</XMI>
